{
  "title": "Goals: • Inspire keen interest in mathematics, science, engineering, and technology, develop strong scholarship in the subject and promote the enjoyment of these studies in high school",
  "outline": [
    {
      "level": "H1",
      "text": "Goals: • Inspire keen interest in mathematics, science, engineering, and technology, develop strong scholarship in the subject and promote the enjoyment of these studies in high school",
      "page": 1
    },
    {
      "level": "H1",
      "text": "• Expose students to potential career opportunities in the field",
      "page": 1
    },
    {
      "level": "H1",
      "text": "• Encourage students to pursue higher education and major in STEM careers",
      "page": 1
    },
    {
      "level": "H1",
      "text": "• Promote interactions with STEM professionals to learn about future opportunities",
      "page": 1
    },
    {
      "level": "H1",
      "text": "• Support field experiences connected to the world outside of the school building",
      "page": 1
    },
    {
      "level": "H1",
      "text": "• Signal to employers, universities, training programs, and military that a student has completed a comprehensive course of study in a specialized area",
      "page": 1
    },
    {
      "level": "H1",
      "text": "• Cultivate transferable work habits such as perseverance, goal setting, and self-direction",
      "page": 1
    },
    {
      "level": "H1",
      "text": "PATHWAY OPTIONS REGULAR PATHWAY 4 credits of Math 4 credits of Science 4 credits of STEM-designated electives ● ● ● ● Maintain an overall 2",
      "page": 1
    },
    {
      "level": "H1",
      "text": "85 GPA ● Participate in a minimum of 3 STEM presentations/conferences each year with a required minimum total of 12 presentations/conferences throughout the 4 years",
      "page": 1
    },
    {
      "level": "H1",
      "text": "* Join and actively participate in a STEM-related extracurricular activity or club every year of attendance",
      "page": 1
    },
    {
      "level": "H1",
      "text": "- ● ● ● ● DISTINCTION PATHWAY 4 credits of Math - At least one math course should be an AP Math class",
      "page": 1
    },
    {
      "level": "H1",
      "text": "4 credits of Science- At least one science course should be an AP Science class",
      "page": 1
    },
    {
      "level": "H1",
      "text": "4 credits of STEM-designated electives - One must be a Computer Science/Technology Class ● Maintain an overall 3",
      "page": 1
    },
    {
      "level": "H1",
      "text": "5 GPA ● Participate in a minimum of 3 STEM presentations/conferences a year with a required minimum total of 12 presentations/conferences throughout the 4 years",
      "page": 1
    },
    {
      "level": "H1",
      "text": "Join and actively participate in a STEM-related extracurricular activity or club every year of attendance",
      "page": 1
    },
    {
      "level": "H1",
      "text": "Either participate in an internship or design and implement a community impact project",
      "page": 1
    }
  ]
}